kicad_tools/__init__.py
kicad_tools/config.py
kicad_tools/dev.py
kicad_tools/exceptions.py
kicad_tools/progress.py
kicad_tools/project.py
kicad_tools/py.typed
kicad_tools/units.py
kicad_tools/analysis/__init__.py
kicad_tools/analysis/complexity.py
kicad_tools/analysis/congestion.py
kicad_tools/analysis/net_status.py
kicad_tools/analysis/signal_integrity.py
kicad_tools/analysis/thermal.py
kicad_tools/analysis/trace_length.py
kicad_tools/assembly/__init__.py
kicad_tools/assembly/validation.py
kicad_tools/audit/__init__.py
kicad_tools/audit/auditor.py
kicad_tools/benchmark/__init__.py
kicad_tools/benchmark/cases.py
kicad_tools/benchmark/generators.py
kicad_tools/benchmark/regression.py
kicad_tools/benchmark/result.py
kicad_tools/benchmark/runner.py
kicad_tools/cli/__init__.py
kicad_tools/cli/__main__.py
kicad_tools/cli/analyze_cmd.py
kicad_tools/cli/audit_cmd.py
kicad_tools/cli/bom_cmd.py
kicad_tools/cli/build_cmd.py
kicad_tools/cli/build_native_cmd.py
kicad_tools/cli/check_cmd.py
kicad_tools/cli/check_parts.py
kicad_tools/cli/clean_cmd.py
kicad_tools/cli/config_cmd.py
kicad_tools/cli/constraints_cmd.py
kicad_tools/cli/datasheet_cmd.py
kicad_tools/cli/decisions_cmd.py
kicad_tools/cli/drc_cmd.py
kicad_tools/cli/drc_summary.py
kicad_tools/cli/erc_cmd.py
kicad_tools/cli/erc_explain_cmd.py
kicad_tools/cli/explain_cmd.py
kicad_tools/cli/export_gerbers.py
kicad_tools/cli/export_netlist.py
kicad_tools/cli/fab_rules_cmd.py
kicad_tools/cli/fix_vias_cmd.py
kicad_tools/cli/footprint_cmd.py
kicad_tools/cli/footprint_generate.py
kicad_tools/cli/generate_bom.py
kicad_tools/cli/init_cmd.py
kicad_tools/cli/interactive.py
kicad_tools/cli/lib.py
kicad_tools/cli/lib_footprints.py
kicad_tools/cli/lib_list_symbols.py
kicad_tools/cli/mfr.py
kicad_tools/cli/mfr_dru.py
kicad_tools/cli/mistakes_cmd.py
kicad_tools/cli/modify_schematic.py
kicad_tools/cli/net_status_cmd.py
kicad_tools/cli/netlist_cmd.py
kicad_tools/cli/nets.py
kicad_tools/cli/optimize_cmd.py
kicad_tools/cli/parser.py
kicad_tools-0.10.2.dist-info/METADATA
kicad_tools-0.10.2.dist-info/WHEEL
kicad_tools-0.10.2.dist-info/entry_points.txt
kicad_tools-0.10.2.dist-info/licenses/LICENSE
kicad_tools-0.10.2.dist-info/RECORD
