Metadata-Version: 2.4
Name: kicad-tools
Version: 0.10.2
Summary: Standalone Python tools for parsing and manipulating KiCad schematic and PCB files
Project-URL: Homepage, https://github.com/rjwalters/kicad-tools
Project-URL: Repository, https://github.com/rjwalters/kicad-tools
Project-URL: Issues, https://github.com/rjwalters/kicad-tools/issues
Author: RJ Walters
License-Expression: MIT
License-File: LICENSE
Keywords: automation,drc,eda,electronics,erc,hardware,kicad,pcb,schematic
Classifier: Development Status :: 4 - Beta
Classifier: Environment :: Console
Classifier: Intended Audience :: Developers
Classifier: Intended Audience :: Manufacturing
Classifier: License :: OSI Approved :: MIT License
Classifier: Operating System :: OS Independent
Classifier: Programming Language :: Python :: 3
Classifier: Programming Language :: Python :: 3.10
Classifier: Programming Language :: Python :: 3.11
Classifier: Programming Language :: Python :: 3.12
Classifier: Programming Language :: Python :: 3.13
Classifier: Topic :: Scientific/Engineering :: Electronic Design Automation (EDA)
Classifier: Topic :: Software Development :: Libraries :: Python Modules
Requires-Python: >=3.10
Requires-Dist: numpy>=1.24
Requires-Dist: pydantic>=2.0
Requires-Dist: pyyaml>=6.0
Requires-Dist: rich>=13.0
Requires-Dist: tomli>=2.0; python_version < '3.11'
Provides-Extra: all
Requires-Dist: fastmcp<3,>=2.0; extra == 'all'
Requires-Dist: markitdown>=0.1.0; extra == 'all'
Requires-Dist: numpy>=1.24; extra == 'all'
Requires-Dist: pdfplumber>=0.10.0; extra == 'all'
Requires-Dist: pydantic>=2.0; extra == 'all'
Requires-Dist: pymupdf>=1.23.0; extra == 'all'
Requires-Dist: pyyaml>=6.0; extra == 'all'
Requires-Dist: requests>=2.28; extra == 'all'
Requires-Dist: rtree>=1.0; extra == 'all'
Provides-Extra: constraints
Requires-Dist: pyyaml>=6.0; extra == 'constraints'
Provides-Extra: datasheet
Requires-Dist: markitdown>=0.1.0; extra == 'datasheet'
Requires-Dist: pdfplumber>=0.10.0; extra == 'datasheet'
Requires-Dist: pymupdf>=1.23.0; extra == 'datasheet'
Provides-Extra: dev
Requires-Dist: fastmcp<3,>=2.0; extra == 'dev'
Requires-Dist: mypy>=1.0; extra == 'dev'
Requires-Dist: numpy>=1.24; extra == 'dev'
Requires-Dist: pydantic>=2.0; extra == 'dev'
Requires-Dist: pytest-benchmark>=4.0; extra == 'dev'
Requires-Dist: pytest-cov>=4.0; extra == 'dev'
Requires-Dist: pytest>=7.0; extra == 'dev'
Requires-Dist: pyyaml>=6.0; extra == 'dev'
Requires-Dist: requests>=2.28; extra == 'dev'
Requires-Dist: responses>=0.23.0; extra == 'dev'
Requires-Dist: rtree>=1.0; extra == 'dev'
Requires-Dist: ruff>=0.1.0; extra == 'dev'
Provides-Extra: drc
Requires-Dist: rtree>=1.0; extra == 'drc'
Provides-Extra: mcp
Requires-Dist: fastmcp<3,>=2.0; extra == 'mcp'
Requires-Dist: pydantic>=2.0; extra == 'mcp'
Provides-Extra: native
Requires-Dist: cmake>=3.15; extra == 'native'
Requires-Dist: nanobind>=2.0; extra == 'native'
Requires-Dist: ninja>=1.10; extra == 'native'
Requires-Dist: scikit-build-core>=0.8; extra == 'native'
Provides-Extra: parts
Requires-Dist: requests>=2.28; extra == 'parts'
